setup.py
client/__init__.py
client/client.py
client/client/__init__.py
client/client/client_database.py
client/client/client_gui.py
client/client/main_windows.py
client/client/start_dialog.py
client/client/transport.py
client/client/utils.py
client/common/__init__.py
client/common/decos.py
client/common/descriptors.py
client/common/errors.py
client/common/metaclasses.py
client/common/utils.py
client/common/variables.py
client/logs/__init__.py
client/logs/client_log_config.py
meeseng_client.egg-info/PKG-INFO
meeseng_client.egg-info/SOURCES.txt
meeseng_client.egg-info/dependency_links.txt
meeseng_client.egg-info/requires.txt
meeseng_client.egg-info/top_level.txt